{
    "k": {
        "x": {
            "m": {
                "r": {},
                "w": {},
                "t": {},
                "6": {},
                "j": {},
                "h": {},
                "n": {},
                "m": {},
                "7": {},
                "q": {},
                "5": {},
                "0": {},
                "k": {},
                "4": {},
                "1": {},
                "v": {},
                "u": {},
                "d": {},
                "x": {},
                "s": {},
                "9": {},
                "3": {},
                "e": {},
                "y": {},
                "z": {},
                "2": {},
                "p": {}
            },
            "k": {
                "c": {},
                "g": {},
                "b": {},
                "u": {},
                "y": {},
                "f": {},
                "z": {},
                "x": {},
                "w": {},
                "v": {}
            },
            "j": {
                "r": {},
                "p": {},
                "n": {}
            },
            "t": {
                "9": {},
                "8": {},
                "d": {},
                "0": {},
                "3": {},
                "2": {},
                "6": {}
            },
            "s": {
                "8": {},
                "9": {},
                "b": {},
                "c": {}
            },
            "h": {
                "y": {},
                "z": {}
            }
        }
    }
}