{
    "x": {
        "3": {
            "4": {
                "n": {}
            },
            "k": {
                "4": {}
            },
            "d": {
                "2": {},
                "b": {},
                "3": {},
                "g": {}
            },
            "p": {
                "b": {}
            },
            "7": {
                "c": {},
                "f": {}
            },
            "6": {
                "1": {}
            }
        },
        "1": {
            "e": {
                "z": {}
            },
            "d": {
                "q": {},
                "n": {},
                "j": {}
            }
        },
        "2": {
            "v": {
                "q": {}
            },
            "n": {
                "j": {}
            },
            "w": {
                "j": {}
            }
        },
        "9": {
            "0": {
                "x": {},
                "q": {},
                "w": {},
                "r": {}
            }
        },
        "8": {
            "g": {
                "v": {},
                "y": {}
            }
        }
    }
}