{
    "6": {
        "g": {
            "b": {
                "6": {},
                "2": {},
                "1": {},
                "n": {},
                "p": {},
                "4": {},
                "j": {},
                "3": {},
                "0": {},
                "5": {},
                "h": {},
                "q": {},
                "b": {},
                "m": {},
                "s": {},
                "8": {},
                "k": {},
                "d": {},
                "e": {},
                "r": {},
                "9": {},
                "7": {}
            },
            "8": {
                "f": {},
                "8": {},
                "w": {},
                "0": {},
                "3": {},
                "7": {},
                "6": {},
                "p": {},
                "4": {},
                "2": {},
                "n": {},
                "m": {},
                "r": {},
                "k": {},
                "t": {},
                "g": {},
                "5": {},
                "v": {},
                "9": {},
                "q": {},
                "s": {},
                "e": {},
                "y": {},
                "d": {},
                "1": {},
                "u": {},
                "j": {},
                "b": {},
                "c": {},
                "h": {},
                "x": {},
                "z": {}
            },
            "2": {
                "0": {},
                "s": {},
                "k": {},
                "f": {},
                "c": {},
                "8": {},
                "v": {},
                "z": {},
                "j": {},
                "p": {},
                "e": {},
                "h": {},
                "7": {},
                "4": {},
                "d": {},
                "m": {},
                "w": {},
                "t": {},
                "y": {},
                "r": {},
                "u": {},
                "6": {},
                "n": {},
                "3": {},
                "5": {},
                "1": {},
                "2": {},
                "9": {},
                "q": {},
                "x": {},
                "g": {},
                "b": {}
            },
            "0": {
                "x": {},
                "j": {},
                "q": {},
                "r": {},
                "p": {},
                "n": {},
                "z": {},
                "7": {},
                "m": {},
                "h": {},
                "t": {},
                "y": {},
                "w": {},
                "k": {}
            },
            "9": {
                "4": {},
                "n": {},
                "5": {},
                "1": {},
                "h": {},
                "p": {},
                "j": {},
                "r": {},
                "0": {},
                "q": {},
                "3": {},
                "6": {},
                "m": {},
                "7": {},
                "k": {},
                "2": {}
            },
            "3": {
                "n": {},
                "h": {},
                "4": {},
                "p": {},
                "1": {},
                "0": {},
                "j": {},
                "5": {}
            },
            "c": {
                "2": {},
                "0": {}
            }
        },
        "e": {
            "x": {
                "c": {},
                "w": {},
                "s": {},
                "t": {},
                "h": {},
                "8": {},
                "0": {},
                "j": {},
                "n": {},
                "6": {},
                "q": {},
                "u": {},
                "b": {},
                "5": {},
                "4": {},
                "r": {},
                "k": {},
                "7": {},
                "p": {},
                "v": {},
                "1": {},
                "m": {},
                "9": {},
                "z": {},
                "d": {},
                "y": {},
                "e": {},
                "2": {},
                "3": {},
                "x": {},
                "g": {},
                "f": {}
            },
            "y": {
                "c": {},
                "n": {},
                "q": {},
                "x": {},
                "5": {},
                "v": {},
                "3": {},
                "y": {},
                "t": {},
                "z": {},
                "j": {},
                "7": {},
                "2": {},
                "4": {},
                "k": {},
                "e": {},
                "p": {},
                "1": {},
                "d": {},
                "b": {},
                "f": {},
                "w": {},
                "g": {},
                "u": {},
                "m": {},
                "9": {},
                "s": {},
                "h": {},
                "0": {},
                "6": {},
                "r": {},
                "8": {}
            },
            "t": {
                "y": {},
                "x": {},
                "z": {},
                "t": {},
                "w": {},
                "v": {},
                "q": {},
                "p": {},
                "r": {},
                "u": {},
                "g": {}
            },
            "r": {
                "z": {},
                "f": {},
                "y": {},
                "r": {},
                "x": {},
                "b": {},
                "d": {},
                "e": {},
                "8": {},
                "w": {},
                "k": {},
                "v": {},
                "u": {},
                "j": {},
                "c": {},
                "q": {},
                "2": {},
                "h": {},
                "t": {},
                "9": {},
                "m": {},
                "s": {},
                "1": {},
                "5": {},
                "7": {},
                "4": {},
                "0": {},
                "g": {},
                "6": {},
                "3": {},
                "p": {},
                "n": {}
            },
            "v": {
                "x": {},
                "j": {},
                "k": {},
                "4": {},
                "1": {},
                "g": {},
                "s": {},
                "u": {},
                "0": {},
                "b": {},
                "w": {},
                "y": {},
                "h": {},
                "9": {},
                "m": {},
                "q": {},
                "v": {},
                "p": {},
                "8": {},
                "c": {},
                "r": {},
                "z": {},
                "3": {},
                "f": {},
                "t": {},
                "6": {},
                "7": {},
                "n": {},
                "e": {},
                "2": {},
                "5": {},
                "d": {}
            },
            "z": {
                "4": {},
                "h": {},
                "p": {},
                "7": {},
                "d": {},
                "0": {},
                "j": {},
                "c": {},
                "s": {},
                "z": {},
                "w": {},
                "y": {},
                "5": {},
                "e": {},
                "6": {},
                "2": {},
                "f": {},
                "n": {},
                "8": {},
                "9": {},
                "m": {},
                "g": {},
                "q": {},
                "u": {},
                "x": {},
                "1": {},
                "k": {},
                "v": {},
                "r": {},
                "t": {},
                "3": {},
                "b": {}
            },
            "u": {
                "n": {},
                "p": {},
                "j": {},
                "r": {},
                "g": {},
                "y": {},
                "c": {},
                "s": {},
                "m": {},
                "d": {},
                "f": {},
                "u": {},
                "w": {},
                "z": {},
                "v": {},
                "x": {},
                "k": {},
                "t": {},
                "q": {},
                "e": {},
                "b": {},
                "8": {},
                "3": {},
                "5": {},
                "h": {},
                "7": {},
                "6": {},
                "9": {}
            },
            "p": {
                "j": {},
                "k": {},
                "y": {},
                "z": {},
                "w": {},
                "v": {},
                "m": {},
                "t": {},
                "n": {},
                "p": {},
                "r": {},
                "q": {},
                "x": {},
                "g": {},
                "7": {},
                "h": {},
                "e": {},
                "s": {},
                "5": {},
                "u": {}
            },
            "w": {
                "s": {},
                "r": {},
                "t": {},
                "p": {},
                "q": {},
                "u": {},
                "j": {},
                "7": {},
                "g": {},
                "m": {},
                "v": {},
                "h": {},
                "k": {},
                "w": {},
                "y": {},
                "z": {},
                "x": {},
                "n": {},
                "f": {},
                "e": {},
                "5": {},
                "b": {},
                "c": {},
                "4": {},
                "d": {},
                "6": {},
                "9": {}
            },
            "n": {
                "v": {},
                "w": {},
                "z": {},
                "y": {},
                "t": {},
                "k": {},
                "q": {},
                "u": {},
                "m": {},
                "s": {},
                "r": {},
                "x": {}
            },
            "q": {
                "f": {},
                "b": {},
                "c": {},
                "9": {},
                "v": {},
                "d": {},
                "z": {},
                "g": {},
                "8": {},
                "e": {},
                "y": {},
                "u": {}
            },
            "g": {
                "z": {},
                "x": {},
                "v": {},
                "y": {},
                "u": {}
            },
            "s": {
                "z": {}
            }
        },
        "s": {
            "p": {
                "b": {},
                "8": {},
                "2": {},
                "0": {},
                "3": {},
                "c": {},
                "1": {},
                "f": {},
                "9": {},
                "4": {}
            },
            "n": {
                "j": {},
                "r": {},
                "2": {},
                "t": {},
                "p": {},
                "5": {},
                "0": {},
                "h": {},
                "4": {},
                "1": {},
                "b": {},
                "6": {},
                "7": {},
                "w": {},
                "c": {},
                "k": {},
                "8": {},
                "s": {},
                "3": {},
                "q": {},
                "d": {},
                "n": {},
                "e": {},
                "x": {},
                "9": {},
                "m": {},
                "f": {},
                "z": {},
                "g": {},
                "y": {},
                "u": {},
                "v": {}
            },
            "h": {
                "h": {},
                "u": {},
                "w": {},
                "5": {},
                "j": {},
                "d": {},
                "9": {},
                "r": {},
                "4": {},
                "x": {},
                "t": {},
                "1": {},
                "g": {},
                "v": {},
                "e": {},
                "c": {},
                "3": {},
                "p": {},
                "y": {},
                "k": {},
                "b": {},
                "z": {},
                "8": {},
                "n": {},
                "2": {},
                "m": {},
                "0": {},
                "s": {},
                "f": {},
                "6": {},
                "q": {},
                "7": {}
            },
            "j": {
                "5": {},
                "w": {},
                "m": {},
                "c": {},
                "d": {},
                "g": {},
                "u": {},
                "b": {},
                "4": {},
                "0": {},
                "1": {},
                "v": {},
                "7": {},
                "s": {},
                "6": {},
                "2": {},
                "n": {},
                "9": {},
                "r": {},
                "8": {},
                "x": {},
                "q": {},
                "h": {},
                "y": {},
                "j": {},
                "p": {},
                "3": {},
                "k": {},
                "z": {},
                "f": {},
                "t": {},
                "e": {}
            },
            "k": {
                "x": {},
                "9": {},
                "4": {},
                "7": {},
                "d": {},
                "b": {},
                "q": {},
                "t": {},
                "c": {},
                "6": {},
                "y": {},
                "0": {},
                "r": {},
                "s": {},
                "z": {},
                "k": {},
                "e": {},
                "2": {},
                "h": {},
                "3": {},
                "f": {},
                "5": {},
                "w": {},
                "u": {},
                "j": {},
                "g": {},
                "8": {},
                "1": {},
                "v": {},
                "m": {},
                "n": {},
                "p": {}
            },
            "m": {
                "5": {},
                "j": {},
                "7": {},
                "p": {},
                "1": {},
                "8": {},
                "d": {},
                "n": {},
                "4": {},
                "v": {},
                "w": {},
                "9": {},
                "6": {},
                "y": {},
                "r": {},
                "z": {},
                "0": {},
                "t": {},
                "3": {},
                "f": {},
                "e": {},
                "h": {},
                "c": {},
                "g": {},
                "m": {},
                "2": {},
                "u": {},
                "q": {},
                "s": {},
                "x": {},
                "b": {},
                "k": {}
            },
            "q": {
                "q": {},
                "8": {},
                "6": {},
                "0": {},
                "j": {},
                "4": {},
                "2": {},
                "k": {},
                "1": {},
                "5": {},
                "p": {},
                "h": {},
                "m": {},
                "n": {},
                "7": {},
                "3": {},
                "9": {},
                "d": {},
                "b": {},
                "t": {},
                "g": {},
                "c": {},
                "r": {},
                "f": {},
                "w": {},
                "e": {},
                "s": {},
                "x": {}
            },
            "t": {
                "3": {},
                "c": {},
                "9": {},
                "b": {},
                "8": {},
                "2": {},
                "0": {},
                "d": {},
                "4": {},
                "1": {},
                "f": {},
                "6": {}
            },
            "7": {
                "c": {},
                "b": {},
                "f": {},
                "8": {},
                "u": {},
                "e": {},
                "g": {},
                "v": {},
                "9": {},
                "y": {},
                "d": {}
            },
            "5": {
                "v": {},
                "z": {},
                "u": {},
                "c": {},
                "f": {},
                "g": {},
                "b": {},
                "y": {},
                "6": {},
                "8": {},
                "3": {},
                "9": {},
                "w": {},
                "e": {},
                "s": {},
                "d": {},
                "x": {},
                "t": {}
            },
            "w": {
                "0": {},
                "1": {},
                "3": {},
                "2": {},
                "4": {}
            },
            "s": {
                "b": {},
                "8": {},
                "0": {},
                "2": {},
                "c": {},
                "9": {}
            }
        },
        "u": {
            "0": {
                "0": {},
                "2": {},
                "1": {},
                "3": {}
            }
        }
    }
}